{
  "resourceType": "CodeSystem",
  "id": "1.3.6.1.4.1.19376.1.2.5.1",
  "url": "1.3.6.1.4.1.19376.1.2.5.1",
  "name": "IHE_mACM_Mobile_Report_Alert_Category",
  "title": "IHE mACM: Mobile Report Alert Category",
  "status": "active",
  "publisher": "IHE",
  "contact": [
    {
      "telecom": [
        {
          "system": "url",
          "value": "http://ihe.net"
        }
      ]
    }
  ],
  "description": "IHE mACM CodeSystem for: Mobile Report Alert Category",
  "content": "complete",
  "concept": [
    {
      "code": "alert",
      "display": "Alert",
			"definition": "Signifies that this communication is intended to be disseminated by the Alert Aggregator according to the expected actions defined in IHE mACM Section 3.84.4.1.3."
    },
    {
      "code": "pcd-alert",
      "display": "PCD Alert",
			"definition": "Signifies that this communication is intended to be disseminated by the Alert Aggregator according to the expected actions defined in IHE mACM Section 3.84.4.1.3 and disseminated according to the Disseminate and Report Alert Status Option. For example, when the Alert Reporter wants the message disseminated by the in-house PCD system rather than the general contact method."
    }
  ]
}
